MANIFEST.in
README.txt
setup.py
docs/HISTORY.txt
docs/HISTORY.txt~
inqbus/__init__.py
inqbus/__init__.pyc
inqbus.collection.proxy.egg-info/PKG-INFO
inqbus.collection.proxy.egg-info/SOURCES.txt
inqbus.collection.proxy.egg-info/dependency_links.txt
inqbus.collection.proxy.egg-info/entry_points.txt
inqbus.collection.proxy.egg-info/namespace_packages.txt
inqbus.collection.proxy.egg-info/not-zip-safe
inqbus.collection.proxy.egg-info/requires.txt
inqbus.collection.proxy.egg-info/top_level.txt
inqbus/collection/__init__.py
inqbus/collection/__init__.pyc
inqbus/collection/proxy/__init__.py
inqbus/collection/proxy/__init__.pyc
inqbus/collection/proxy/configure.zcml
inqbus/collection/proxy/configure.zcml~
inqbus/collection/proxy/skins.zcml
inqbus/collection/proxy/skins.zcml~
inqbus/collection/proxy/traversal.py
inqbus/collection/proxy/traversal.pyc
inqbus/collection/proxy/traversal.py~
inqbus/collection/proxy/browser/__init__.py
inqbus/collection/proxy/browser/__init__.pyc
inqbus/collection/proxy/browser/collectionproxyview.pt
inqbus/collection/proxy/browser/collectionproxyview.py
inqbus/collection/proxy/browser/collectionproxyview.pyc
inqbus/collection/proxy/browser/collectionproxyview.py~
inqbus/collection/proxy/browser/configure.zcml
inqbus/collection/proxy/browser/configure.zcml~
inqbus/collection/proxy/content/__init__.py
inqbus/collection/proxy/content/__init__.pyc
inqbus/collection/proxy/content/configure.zcml
inqbus/collection/proxy/content/configure.zcml~
inqbus/collection/proxy/content/extender.py
inqbus/collection/proxy/content/extender.pyc
inqbus/collection/proxy/content/extender.py~
inqbus/collection/proxy/profiles/default/skins.xml
inqbus/collection/proxy/profiles/default/skins.xml~
inqbus/collection/proxy/skins/collection_proxy_custom_templates/folder_listing.pt
inqbus/collection/proxy/skins/collection_proxy_custom_templates/folder_listing.pt~
inqbus/collection/proxy/tests/__init__.py
inqbus/collection/proxy/tests/__init__.pyc
inqbus/collection/proxy/tests/base.py
inqbus/collection/proxy/tests/base.pyc
inqbus/collection/proxy/tests/base.py~
inqbus/collection/proxy/tests/configure.zcml
inqbus/collection/proxy/tests/test_functionalities.py
inqbus/collection/proxy/tests/test_functionalities.pyc
inqbus/collection/proxy/tests/test_functionalities.py~