Metadata-Version: 1.0
Name: inqbus.collection.proxy
Version: 1.0b1
Summary: UNKNOWN
Home-page: http://svn.plone.org/svn/collective/
Author: Max Brauer
Author-email: max.brauer@inqbus.de
License: GPL
Platform: UNKNOWN
Classifier: Programming Language :: Python
